qiita/__init__.py
qiita/client.py
qiita/v2/__init__.py
qiita/v2/api_client.py
qiita/v2/api_response.py
qiita/v2/configuration.py
qiita/v2/exceptions.py
qiita/v2/py.typed
qiita/v2/rest.py
qiita/v2/api/__init__.py
qiita/v2/api/team_api.py
qiita/v2/api/user_api.py
qiita/v2/models/__init__.py
qiita/v2/models/add_group_member_request.py
qiita/v2/models/authenticated_user.py
qiita/v2/models/comment.py
qiita/v2/models/create_comment_request.py
qiita/v2/models/create_group_request.py
qiita/v2/models/create_imported_comment_request.py
qiita/v2/models/create_item_request.py
qiita/v2/models/delete_group_member_request.py
qiita/v2/models/get_authenticated_user_items_response_inner.py
qiita/v2/models/get_authenticated_user_items_response_inner_group.py
qiita/v2/models/get_authenticated_user_items_response_inner_tags_inner.py
qiita/v2/models/get_authenticated_user_items_response_inner_team_membership.py
qiita/v2/models/get_authenticated_user_items_response_inner_user.py
qiita/v2/models/group.py
qiita/v2/models/group_member.py
qiita/v2/models/issue_access_token_request.py
qiita/v2/models/issue_access_token_response.py
qiita/v2/models/item.py
qiita/v2/models/item_tag.py
qiita/v2/models/item_team_membership.py
qiita/v2/models/like_history.py
qiita/v2/models/update_comment_request.py
qiita/v2/models/update_group_request.py
qiita/v2/models/update_item_request.py
qiita/v2/models/user.py
test/__init__.py
test/test_add_group_member_request.py
test/test_authenticated_user.py
test/test_comment.py
test/test_create_comment_request.py
test/test_create_group_request.py
test/test_create_imported_comment_request.py
test/test_create_item_request.py
test/test_delete_group_member_request.py
test/test_get_authenticated_user_items_response_inner.py
test/test_get_authenticated_user_items_response_inner_group.py
test/test_get_authenticated_user_items_response_inner_tags_inner.py
test/test_get_authenticated_user_items_response_inner_team_membership.py
qiita_sdk-1.1.dist-info/METADATA
qiita_sdk-1.1.dist-info/WHEEL
qiita_sdk-1.1.dist-info/top_level.txt
qiita_sdk-1.1.dist-info/RECORD
