Metadata-Version: 2.1
Name: qiita-sdk
Version: 1.1
Summary: Qiita SDK for Pyrhon
Home-page: https://github.com/nanato12/qiita-sdk-python
Author: nanato12
Author-email: admin@okj.info
Maintainer: nanato12
Maintainer-email: admin@okj.info
License: MIT License
Keywords: qiita qiita-sdk
Classifier: License :: OSI Approved :: MIT License
Classifier: Intended Audience :: Developers
Classifier: Programming Language :: Python :: 3
Classifier: Programming Language :: Python :: 3 :: Only
Classifier: Programming Language :: Python :: 3.8
Classifier: Programming Language :: Python :: 3.9
Classifier: Programming Language :: Python :: 3.10
Classifier: Programming Language :: Python :: 3.11
Classifier: Programming Language :: Python :: 3.12
Classifier: Topic :: Software Development
Requires-Python: >=3.8
Requires-Dist: python-dateutil>=2.5.3
Requires-Dist: setuptools>=21.0.0
Requires-Dist: urllib3<2.1.0,>=1.25.3
Requires-Dist: pydantic>=2
Requires-Dist: typing-extensions>=4.7.1
